terratorch_surya/__init__.py
terratorch_surya/datasets/__init__.py
terratorch_surya/datasets/helio.py
terratorch_surya/datasets/transformations.py
terratorch_surya/downstream_examples/README.md
terratorch_surya/downstream_examples/__init__.py
terratorch_surya/downstream_examples/download_data.py
terratorch_surya/downstream_examples/download_sample_train_data.py
terratorch_surya/downstream_examples/ar_segmentation/README.md
terratorch_surya/downstream_examples/ar_segmentation/__init__.py
terratorch_surya/downstream_examples/ar_segmentation/config.yaml
terratorch_surya/downstream_examples/ar_segmentation/config_infer.yaml
terratorch_surya/downstream_examples/ar_segmentation/create_ar_csv.py
terratorch_surya/downstream_examples/ar_segmentation/dataset.py
terratorch_surya/downstream_examples/ar_segmentation/download_data.sh
terratorch_surya/downstream_examples/ar_segmentation/finetune.py
terratorch_surya/downstream_examples/ar_segmentation/infer.py
terratorch_surya/downstream_examples/ar_segmentation/models.py
terratorch_surya/downstream_examples/ar_segmentation/assets/.gitkeep
terratorch_surya/downstream_examples/euv_spectra_prediction/README.md
terratorch_surya/downstream_examples/euv_spectra_prediction/__init__.py
terratorch_surya/downstream_examples/euv_spectra_prediction/config.yaml
terratorch_surya/downstream_examples/euv_spectra_prediction/config_infer.yaml
terratorch_surya/downstream_examples/euv_spectra_prediction/dataset.py
terratorch_surya/downstream_examples/euv_spectra_prediction/download_data.sh
terratorch_surya/downstream_examples/euv_spectra_prediction/finetune.py
terratorch_surya/downstream_examples/euv_spectra_prediction/infer.py
terratorch_surya/downstream_examples/euv_spectra_prediction/models.py
terratorch_surya/downstream_examples/euv_spectra_prediction/assets/.gitkeep
terratorch_surya/downstream_examples/solar_flare_forecasting/README.md
terratorch_surya/downstream_examples/solar_flare_forecasting/__init__.py
terratorch_surya-0.1.0.dist-info/METADATA
terratorch_surya-0.1.0.dist-info/WHEEL
terratorch_surya-0.1.0.dist-info/entry_points.txt
terratorch_surya-0.1.0.dist-info/licenses/LICENSE
terratorch_surya-0.1.0.dist-info/RECORD
