Metadata-Version: 2.4
Name: terratorch_surya
Version: 0.1.0
Summary: Implementation of the Surya Foundation Model and Downstream Tasks for Heliophysics
Project-URL: Repository, https://github.com/NASA-IMPACT/Surya
Project-URL: Issues, https://github.com/NASA-IMPACT/Surya/issues
Author: Surya Team
Maintainer: Surya Team
License:                                  Apache License
License-File: LICENSE
Keywords: deep learning,forecasting,foundation model,heliophysics,pytorch,solar dynamics,solar wind,spectformer,transformer
Classifier: Intended Audience :: Science/Research
Classifier: Operating System :: OS Independent
Classifier: Programming Language :: Python :: 3
Classifier: Programming Language :: Python :: 3.11
Classifier: Programming Language :: Python :: 3.12
Classifier: Topic :: Scientific/Engineering
Classifier: Topic :: Scientific/Engineering :: Artificial Intelligence
Classifier: Topic :: Scientific/Engineering :: Astronomy
Classifier: Topic :: Scientific/Engineering :: Physics
Requires-Python: >=3.11
Requires-Dist: einops>=0.4.0
Requires-Dist: h5netcdf>=1.6.4
Requires-Dist: hdf5plugin>=3.0.0
Requires-Dist: hf-transfer>=0.1.9
Requires-Dist: huggingface-hub>=0.10.0
Requires-Dist: ipykernel>=6.30.1
Requires-Dist: matplotlib>=3.5.0
Requires-Dist: mpl-animators>=1.2.4
Requires-Dist: numba>=0.56.0
Requires-Dist: numpy>=1.21.0
Requires-Dist: packaging>=21.0
Requires-Dist: pandas>=1.3.0
Requires-Dist: peft>=0.4.0
Requires-Dist: pytest>=8.4.1
Requires-Dist: pyyaml>=5.4.0
Requires-Dist: scikit-image>=0.19.0
Requires-Dist: sunpy>=4.0.0
Requires-Dist: timm>=0.9.0
Requires-Dist: torch>=2.6.0
Requires-Dist: torchaudio>=2.6.0
Requires-Dist: torchvision>=0.21.0
Requires-Dist: wandb>=0.15.0
Requires-Dist: xarray>=0.20.0
Provides-Extra: all
Requires-Dist: black>=24.0.0; extra == 'all'
Requires-Dist: flake8>=4.0.0; extra == 'all'
Requires-Dist: ipykernel>=6.0.0; extra == 'all'
Requires-Dist: ipywidgets>=7.6.0; extra == 'all'
Requires-Dist: isort>=5.10.0; extra == 'all'
Requires-Dist: jupyter>=1.0.0; extra == 'all'
Requires-Dist: mypy>=1.8.0; extra == 'all'
Requires-Dist: myst-parser>=0.17.0; extra == 'all'
Requires-Dist: plotly>=5.0.0; extra == 'all'
Requires-Dist: pre-commit>=2.17.0; extra == 'all'
Requires-Dist: pytest-cov>=3.0.0; extra == 'all'
Requires-Dist: pytest>=7.0.0; extra == 'all'
Requires-Dist: seaborn>=0.11.0; extra == 'all'
Requires-Dist: sphinx-autodoc-typehints>=1.12.0; extra == 'all'
Requires-Dist: sphinx-rtd-theme>=1.0.0; extra == 'all'
Requires-Dist: sphinx>=4.0.0; extra == 'all'
Provides-Extra: dev
Requires-Dist: black>=24.0.0; extra == 'dev'
Requires-Dist: flake8>=4.0.0; extra == 'dev'
Requires-Dist: isort>=5.10.0; extra == 'dev'
Requires-Dist: mypy>=1.8.0; extra == 'dev'
Requires-Dist: pre-commit>=2.17.0; extra == 'dev'
Requires-Dist: pytest-cov>=3.0.0; extra == 'dev'
Requires-Dist: pytest>=7.0.0; extra == 'dev'
Provides-Extra: docs
Requires-Dist: myst-parser>=0.17.0; extra == 'docs'
Requires-Dist: sphinx-autodoc-typehints>=1.12.0; extra == 'docs'
Requires-Dist: sphinx-rtd-theme>=1.0.0; extra == 'docs'
Requires-Dist: sphinx>=4.0.0; extra == 'docs'
Provides-Extra: notebook
Requires-Dist: ipykernel>=6.0.0; extra == 'notebook'
Requires-Dist: ipywidgets>=7.6.0; extra == 'notebook'
Requires-Dist: jupyter>=1.0.0; extra == 'notebook'
Provides-Extra: viz
Requires-Dist: plotly>=5.0.0; extra == 'viz'
Requires-Dist: seaborn>=0.11.0; extra == 'viz'
